{
  "title": "Can GameStop Really Buy eBay?",
  "description": "GameStop has made an unsolicited offer to buy eBay for about $56 billion. The proposed deal, which eBay says it is reviewing, is the brainchild of GameStop CEO Ryan Cohen. In an interview with WSJ’s Lauren Thomas, Cohen said that putting his videogame retailer and eBay under one roof could create opportunities to cut costs and improve earnings. Jessica Mendoza hosts.\n\n\n\nFurther Listening: \n\n- To the Moon: How did a bunch of amateurs take Wall Street by surprise?\n\nSign up for WSJ’s free What’s News newsletter.\n\nLearn more about your ad choices. Visit megaphone.fm/adchoices",
  "published": "Fri, 08 May 2026 20:31:00 -0000",
  "audio_url": "https://pdst.fm/e/traffic.megaphone.fm/WSJ2211814165.mp3?updated=1778273526",
  "duration": "1331",
  "link": "",
  "subtitles": [
    {
      "en": "My name is Lauren Thomas and I am a deals and activism reporter here at the Wall Street Journal.",
      "ko": "제 이름은 로렌 토마스이고 월스트리트 저널에서 인수합병 및 행동주의 투자 담당 기자로 일하고 있습니다."
    },
    {
      "en": "And Lauren, we're talking to you because there was a proposed merger and acquisition, proposed deal that caught a lot of people's eyes recently.",
      "ko": "로렌, 최근 많은 사람들의 관심을 끈 인수합병 제안이 있어서 당신과 이야기를 나누고 있습니다."
    },
    {
      "en": "Can you tell us what that is?",
      "ko": "그게 무엇인지 말씀해 주시겠습니까?"
    },
    {
      "en": "Yes.",
      "ko": "네."
    },
    {
      "en": "A headline number for sure, GameStop officially submitted a proposal, a $56 billion proposal to acquire eBay.",
      "ko": "확실히 헤드라인을 장식할 만한 숫자인데요, 게임스톱이 이베이를 인수하기 위한 560억 달러 규모의 제안을 공식적으로 제출했습니다."
    },
    {
      "en": "GameStop, which is worth about $11 billion, was offered to buy a company four times that size, eBay, the commerce giant.",
      "ko": "약 110억 달러 가치의 게임스톱이 그 4배 규모인 전자상거래 거대 기업 이베이를 인수하겠다고 제안한 것입니다."
    },
    {
      "en": "Why did you think when you heard that?",
      "ko": "그 소식을 들었을 때 어떻게 생각하셨나요?"
    },
    {
      "en": "Yeah, I mean, probably like everyone else was scratching my head a little bit.",
      "ko": "네, 아마 다른 모든 사람들처럼 저도 약간 당황스러웠습니다."
    },
    {
      "en": "You don't often see these smaller companies coming out and trying to buy much larger businesses so that in and of itself, I think, provides some shock value.",
      "ko": "이렇게 작은 기업이 나서서 훨씬 큰 기업을 인수하려는 시도는 흔히 볼 수 없는 일이라서, 그 자체로 충격적이라고 생각합니다."
    },
    {
      "en": "So Lauren called the man behind the Sardatius plan, Ryan Cohen, the CEO of GameStop.",
      "ko": "그래서 로렌은 이 대담한 계획의 배후 인물인 게임스톱의 CEO 라이언 코헨에게 전화를 걸었습니다."
    },
    {
      "en": "Walks through like what ultimately led you to eBay?",
      "ko": "궁극적으로 이베이를 선택하게 된 계기를 설명해 주시겠습니까?"
    },
    {
      "en": "I think that eBay under my watch, it really comes down to scale being able to do something big.",
      "ko": "제 생각에 제가 경영하는 이베이는 결국 규모를 키워 큰 일을 할 수 있다는 것으로 귀결됩니다."
    },
    {
      "en": "Right.",
      "ko": "맞습니다."
    },
    {
      "en": "And I think eBay, there's nobody who is more qualified based on my experience to run the eBay business.",
      "ko": "그리고 제 경험을 바탕으로 볼 때 이베이 사업을 운영하는 데 저보다 더 적합한 사람은 없다고 생각합니다."
    },
    {
      "en": "I could turn that business into something worth significantly more than what eBay is today.",
      "ko": "저는 그 사업을 현재의 이베이보다 훨씬 더 가치 있는 것으로 만들 수 있습니다."
    },
    {
      "en": "Yeah.",
      "ko": "네."
    },
    {
      "en": "And I can grow it and I can make it a lot more money in a very short period of time.",
      "ko": "그리고 매우 짧은 시간 안에 그것을 성장시키고 훨씬 더 많은 돈을 벌 수 있습니다."
    },
    {
      "en": "And it could be like a legit competitor down the zone.",
      "ko": "그리고 그 분야에서 진정한 경쟁자가 될 수 있습니다."
    },
    {
      "en": "For Lauren, the deal raises a big question.",
      "ko": "로렌에게 이 거래는 큰 의문을 불러일으킵니다."
    },
    {
      "en": "As an M&A reporter, anytime you see a deal, I'm always asking myself, well, how are they going to pull this off, particularly in terms of financing?",
      "ko": "인수합병 기자로서 거래를 볼 때마다 저는 항상 스스로에게 묻습니다. 특히 자금 조달 측면에서 이들이 어떻게 이것을 성사시킬 것인가?"
    },
    {
      "en": "How are they going to pay for it?",
      "ko": "어떻게 대금을 지불할 것인가?"
    },
    {
      "en": "Welcome to the journal, our show about money, business, and power.",
      "ko": "더 저널에 오신 것을 환영합니다. 돈, 비즈니스, 그리고 권력에 관한 우리의 쇼입니다."
    },
    {
      "en": "I'm Jessica Mendoza.",
      "ko": "저는 제시카 멘도자입니다."
    },
    {
      "en": "It's Friday, May 8th.",
      "ko": "5월 8일 금요일입니다."
    },
    {
      "en": "Coming up on the show, GameStop makes a play for eBay.",
      "ko": "이어지는 내용은 게임스톱이 이베이 인수에 나서다입니다."
    },
    {
      "en": "Amazon Health AI presents Painful Thoughts.",
      "ko": "아마존 헬스 AI가 고통스러운 생각들을 소개합니다."
    },
    {
      "en": "Why did I search the internet for answers to my cold sore problem?",
      "ko": "왜 나는 구순포진 문제의 해답을 찾기 위해 인터넷을 검색했을까?"
    },
    {
      "en": "Now I'm stuck down a rabbit hole filled with images of alarmingly graphic source in various stages of ooze.",
      "ko": "이제 나는 다양한 진물 단계의 충격적으로 적나라한 이미지들로 가득한 토끼굴에 빠져버렸다."
    },
    {
      "en": "I can clear my search history, but I can never unsee that.",
      "ko": "검색 기록은 지울 수 있지만, 본 것은 결코 잊을 수 없다."
    },
    {
      "en": "Don't go down the rabbit hole.",
      "ko": "토끼굴에 빠지지 마세요."
    },
    {
      "en": "Amazon Health AI gets you the right care fast.",
      "ko": "아마존 헬스 AI가 빠르게 올바른 치료를 받게 해드립니다."
    },
    {
      "en": "Health care just got less painful.",
      "ko": "건강 관리가 이제 덜 고통스러워졌습니다."
    },
    {
      "en": "AI is moving fast across the enterprise.",
      "ko": "AI는 기업 전반에 걸쳐 빠르게 확산되고 있습니다."
    },
    {
      "en": "But without visibility, it's just chaos.",
      "ko": "하지만 가시성이 없다면 그것은 그저 혼란일 뿐입니다."
    },
    {
      "en": "Different tools, different models.",
      "ko": "다른 도구, 다른 모델."
    },
    {
      "en": "Different teams using AI in completely different ways.",
      "ko": "다른 팀들이 완전히 다른 방식으로 AI를 사용합니다."
    },
    {
      "en": "ServiceNow turns that chaos into control.",
      "ko": "서비스나우는 그 혼란을 통제로 바꿉니다."
    },
    {
      "en": "With the AI Control Tower, you see all your AI across the business in one place.",
      "ko": "AI 컨트롤 타워를 통해 비즈니스 전반의 모든 AI를 한 곳에서 볼 수 있습니다."
    },
    {
      "en": "What it's doing, what it's done, and what it's about to do.",
      "ko": "무엇을 하고 있는지, 무엇을 했는지, 그리고 무엇을 하려고 하는지."
    },
    {
      "en": "So you stay in control.",
      "ko": "그래서 당신이 통제력을 유지할 수 있습니다."
    },
    {
      "en": "To put AI to work for people, visit serviceNow.com.",
      "ko": "사람들을 위해 AI를 활용하려면 serviceNow.com을 방문하세요."
    },
    {
      "en": "Ryan Cohen got a start with the online pet supply store Chouee, a company he co-founded in 2011 and sold to PetSmart.",
      "ko": "라이언 코헨은 2011년에 공동 창업하고 펫스마트에 매각한 온라인 애완동물 용품점 츄이로 시작했습니다."
    },
    {
      "en": "Since then, he's built an online following as an investor.",
      "ko": "그 이후로 그는 투자자로서 온라인 팔로워를 구축했습니다."
    },
    {
      "en": "And what is the allure around Ryan Cohen?",
      "ko": "라이언 코헨의 매력은 무엇인가요?"
    },
    {
      "en": "I mean, he's not exactly a household name, but he is kind of a cult figure.",
      "ko": "그는 정확히 유명 인사는 아니지만 일종의 컬트적인 인물입니다."
    },
    {
      "en": "Totally.",
      "ko": "정말 그렇습니다."
    },
    {
      "en": "I think what so many people ultimately have found themselves connecting to Ryan and being drawn toward Ryan is he does in a lot of ways kind of represent the everyday average Joe kind of trader investor.",
      "ko": "많은 사람들이 궁극적으로 라이언에게 공감하고 끌리는 이유는 그가 여러 면에서 일상적인 평범한 개인 투자자를 대표하기 때문이라고 생각합니다."
    },
    {
      "en": "He's just kind of your anti Wall Street guy that's definitely struck a court with a lot of people, particularly younger people coming up in this world and trying to find ways to make money on their own.",
      "ko": "그는 일종의 반월스트리트 인물로서 많은 사람들, 특히 이 세상에서 자신만의 방식으로 돈을 벌려고 하는 젊은 사람들의 마음을 확실히 사로잡았습니다."
    },
    {
      "en": "Cohen built that reputation in 2020.",
      "ko": "코헨은 2020년에 그런 명성을 쌓았습니다."
    },
    {
      "en": "When he took an interest in the company that would come to define his career, GameStop.",
      "ko": "그의 경력을 정의하게 될 회사인 게임스톱에 관심을 가지게 되었을 때입니다."
    },
    {
      "en": "Ryan Cohen had been building a stake in this company.",
      "ko": "라이언 코헨은 이 회사의 지분을 축적하고 있었습니다."
    },
    {
      "en": "By then built a pretty significant stake making him one of the biggest shareholders in GameStop.",
      "ko": "그때까지 상당한 지분을 구축하여 게임스톱의 최대 주주 중 한 명이 되었습니다."
    },
    {
      "en": "And he basically showed up and started pushing for changes.",
      "ko": "그리고 그는 기본적으로 나타나서 변화를 추진하기 시작했습니다."
    },
    {
      "en": "He wanted new management.",
      "ko": "그는 새로운 경영진을 원했습니다."
    },
    {
      "en": "He wanted GameStop to rethink things strategically.",
      "ko": "그는 게임스톱이 전략적으로 재고하기를 원했습니다."
    },
    {
      "en": "And it was really an activist play in large part.",
      "ko": "그리고 이것은 상당 부분 행동주의 투자였습니다."
    },
    {
      "en": "He was there.",
      "ko": "그는 그곳에 있었습니다."
    },
    {
      "en": "He was trying to get inside the company himself in some sort of leadership position.",
      "ko": "그는 어떤 형태로든 리더십 직위로 회사 내부에 들어가려고 했습니다."
    },
    {
      "en": "In January 2021, GameStop offered Cohen a seat on the board.",
      "ko": "2021년 1월, 게임스톱은 코헨에게 이사회 자리를 제안했습니다."
    },
    {
      "en": "And around that time, the company's share price exploded.",
      "ko": "그리고 그 무렵, 회사의 주가가 폭등했습니다."
    }
  ],
  "analysis": {
    "summary_ko": "GameStop의 CEO 라이언 코헨이 자사보다 4배 큰 규모의 eBay를 560억 달러에 인수하겠다는 제안을 했습니다. 시가총액 110억 달러의 GameStop이 560억 달러 규모의 eBay 인수를 제안한 것은 매우 이례적인 일입니다. 코헨은 자신의 경험을 바탕으로 eBay를 운영하면 비용 절감과 수익 개선을 통해 현재보다 훨씬 더 가치있는 회사로 만들 수 있다고 주장합니다. 그는 eBay를 Amazon의 정당한 경쟁자로 키울 수 있다고 자신하고 있습니다. 가장 큰 의문은 작은 회사가 어떻게 이 거대한 인수 자금을 조달할 것인가 하는 점입니다.",
    "key_points": [
      "GameStop이 자사 시가총액의 5배에 달하는 560억 달러 규모의 eBay 인수 제안",
      "라이언 코헨 CEO는 규모의 경제와 자신의 경험을 바탕으로 eBay 가치를 크게 높일 수 있다고 주장",
      "소규모 회사의 대규모 인수 제안이라는 이례적 상황으로 인수 자금 조달 방식이 핵심 관심사",
      "코헨은 Chewy 창업자로 PetSmart에 회사를 매각한 경험이 있으며 투자자로서 컬트적 인기 보유"
    ],
    "related_stocks": [
      {
        "ticker": "GME",
        "name": "GameStop Corp.",
        "reason": "eBay 인수 제안의 주체로 공격적인 M&A 전략 추진",
        "sentiment": "positive"
      },
      {
        "ticker": "EBAY",
        "name": "eBay Inc.",
        "reason": "GameStop으로부터 560억 달러 인수 제안을 받았으며 현재 검토 중",
        "sentiment": "neutral"
      },
      {
        "ticker": "AMZN",
        "name": "Amazon.com Inc.",
        "reason": "합병 후 GameStop-eBay가 경쟁 대상으로 지목한 이커머스 시장 선두주자",
        "sentiment": "neutral"
      }
    ],
    "market_outlook": "소규모 기업의 대규모 인수 제안은 자금 조달 가능성에 대한 시장의 회의적 시각을 불러일으킬 가능성이 높습니다. 다만 라이언 코헨의 과거 성공 경험과 밈스톡 투자자들의 강력한 지지 기반은 변수가 될 수 있습니다. 실제 인수 성사 가능성보다는 GameStop의 전략적 방향 전환과 이커머스 시장 재편 가능성에 시장의 관심이 집중될 것으로 보입니다."
  },
  "generated_at": "2026-05-09T14:42:14.570264"
}